LICENSE
README.md
pyproject.toml
setup.py
src/geom_median/__init__.py
src/geom_median.egg-info/PKG-INFO
src/geom_median.egg-info/SOURCES.txt
src/geom_median.egg-info/dependency_links.txt
src/geom_median.egg-info/requires.txt
src/geom_median.egg-info/top_level.txt
src/geom_median/numpy/__init__.py
src/geom_median/numpy/main.py
src/geom_median/numpy/utils.py
src/geom_median/numpy/weiszfeld_array.py
src/geom_median/numpy/weiszfeld_list_of_array.py
src/geom_median/torch/__init__.py
src/geom_median/torch/main.py
src/geom_median/torch/utils.py
src/geom_median/torch/weiszfeld_array.py
src/geom_median/torch/weiszfeld_list_of_array.py