Metadata-Version: 2.1
Name: geom-median
Version: 0.1.0
Summary: Implementation of the smoothed Weiszfeld algorithm to compute the geometric median
Home-page: https://github.com/krishnap25/geom_median
Author: Krishna Pillutla
Author-email: pillutla@cs.washington.edu
License: UNKNOWN
Project-URL: Bug Tracker, https://github.com/krishnap25/geom_median/issues
Platform: UNKNOWN
Classifier: Programming Language :: Python :: 3
Classifier: License :: OSI Approved :: GNU General Public License v3 (GPLv3)
Classifier: Operating System :: OS Independent
Requires-Python: >=3.6
License-File: LICENSE
